{
  "id": "3683609",
  "name": "EachStar",
  "font_family": "iconfont",
  "css_prefix_text": "icon-",
  "description": "",
  "glyphs": [
    {
      "icon_id": "12321559",
      "name": "云盘",
      "font_class": "yunpan",
      "unicode": "e62c",
      "unicode_decimal": 58924
    },
    {
      "icon_id": "1000860",
      "name": "qq",
      "font_class": "qq",
      "unicode": "e62e",
      "unicode_decimal": 58926
    },
    {
      "icon_id": "1148896",
      "name": "邮箱",
      "font_class": "youxiang",
      "unicode": "e687",
      "unicode_decimal": 59015
    },
    {
      "icon_id": "7714975",
      "name": "github",
      "font_class": "github",
      "unicode": "e63a",
      "unicode_decimal": 58938
    },
    {
      "icon_id": "5288587",
      "name": "垃圾桶",
      "font_class": "lajitong",
      "unicode": "e66b",
      "unicode_decimal": 58987
    },
    {
      "icon_id": "566213",
      "name": "发布",
      "font_class": "fabu",
      "unicode": "e643",
      "unicode_decimal": 58947
    },
    {
      "icon_id": "7976573",
      "name": "累计次数",
      "font_class": "leijicishu",
      "unicode": "e689",
      "unicode_decimal": 59017
    },
    {
      "icon_id": "6265091",
      "name": "积分",
      "font_class": "bonus-line",
      "unicode": "e649",
      "unicode_decimal": 58953
    },
    {
      "icon_id": "26974789",
      "name": "次数",
      "font_class": "cishu",
      "unicode": "e626",
      "unicode_decimal": 58918
    },
    {
      "icon_id": "364434",
      "name": "放大镜",
      "font_class": "fangdajing",
      "unicode": "e617",
      "unicode_decimal": 58903
    },
    {
      "icon_id": "658017",
      "name": "个人",
      "font_class": "geren",
      "unicode": "e657",
      "unicode_decimal": 58967
    },
    {
      "icon_id": "954918",
      "name": "时间",
      "font_class": "shijian",
      "unicode": "e6d3",
      "unicode_decimal": 59091
    },
    {
      "icon_id": "8288894",
      "name": "星星",
      "font_class": "xingxing",
      "unicode": "e859",
      "unicode_decimal": 59481
    },
    {
      "icon_id": "8289033",
      "name": "星星",
      "font_class": "xingxing1",
      "unicode": "e870",
      "unicode_decimal": 59504
    }
  ]
}
